alchemista/__init__.py
alchemista/config.py
alchemista/field.py
alchemista/func.py
alchemista/main.py
alchemista/model.py
alchemista/py.typed
alchemista/typing.py
alchemista-0.3.0.dist-info/LICENSE
alchemista-0.3.0.dist-info/WHEEL
alchemista-0.3.0.dist-info/METADATA
alchemista-0.3.0.dist-info/RECORD
