Metadata-Version: 2.1
Name: alchemista
Version: 0.3.0
Summary: Tools to convert SQLAlchemy models to Pydantic models
Home-page: https://github.com/ggabriel96/alchemista
License: MIT
Author: Gabriel Galli
Author-email: ggabriel96@hotmail.com
Requires-Python: >=3.8,<4.0
Classifier: License :: OSI Approved :: MIT License
Classifier: Programming Language :: Python :: 3
Classifier: Programming Language :: Python :: 3.8
Classifier: Programming Language :: Python :: 3.9
Requires-Dist: Deprecated (>=1.2.12,<2.0.0)
Requires-Dist: SQLAlchemy (>=1.4.14,<2.0.0)
Requires-Dist: pydantic (>=1.8.1,<2.0.0)
Project-URL: Repository, https://github.com/ggabriel96/alchemista
